statcheck/__init__.py
statcheck/calc_APA_factor.py
statcheck/checkdir.py
statcheck/compute_p.py
statcheck/decision_error_test.py
statcheck/error_test.py
statcheck/extract_1tail.py
statcheck/extract_stats.py
statcheck/file_to_txt.py
statcheck/helpers_parse_stats.py
statcheck/plot_statcheck.py
statcheck/process_stats.py
statcheck/regex.py
statcheck/st.py
statcheck/sum_st.py
statcheck-0.0.7.dist-info/licenses/LICENSE.txt
statcheck-0.0.7.dist-info/METADATA
statcheck-0.0.7.dist-info/WHEEL
statcheck-0.0.7.dist-info/top_level.txt
statcheck-0.0.7.dist-info/RECORD
