Metadata-Version: 2.4
Name: statcheck
Version: 0.0.7
Summary: Python implementation of the R package 'statcheck' used for extracting and analysing statistical tests in scientific articles.
Author-email: Hubert Plisiecki <hplisiecki@gmail.com>
License:                     GNU GENERAL PUBLIC LICENSE
Project-URL: Homepage, https://github.com/hplisiecki/statcheck_python
Project-URL: Source, https://github.com/hplisiecki/statcheck_python
Project-URL: Issues, https://github.com/hplisiecki/statcheck_python/issues
Classifier: Programming Language :: Python :: 3
Classifier: Programming Language :: Python :: 3 :: Only
Classifier: Programming Language :: Python :: 3.9
Classifier: Programming Language :: Python :: 3.10
Classifier: Programming Language :: Python :: 3.11
Classifier: Programming Language :: Python :: 3.12
Classifier: Programming Language :: Python :: 3.13
Classifier: License :: OSI Approved :: GNU General Public License v2 (GPLv2)
Classifier: Operating System :: OS Independent
Classifier: Intended Audience :: Science/Research
Classifier: Topic :: Scientific/Engineering :: Information Analysis
Requires-Python: >=3.9
License-File: LICENSE.txt
Requires-Dist: numpy>=1.26
Requires-Dist: pandas>=1.5
Requires-Dist: scipy>=1.11
Requires-Dist: tqdm>=4.65
Requires-Dist: beautifulsoup4>=4.11
Requires-Dist: PyPDF2>=2.12
Requires-Dist: matplotlib>=3.8
Provides-Extra: dev
Requires-Dist: pytest>=7; extra == "dev"
Requires-Dist: pytest-cov>=4; extra == "dev"
Requires-Dist: ruff>=0.5; extra == "dev"
Requires-Dist: pyupgrade>=3.15; extra == "dev"
Dynamic: license-file
